pysampling/__init__.py
pysampling/measures.py
pysampling/sample.py
pysampling/sampling.py
pysampling/usage.py
pysampling/util.py
pysampling/version.py
pysampling/algorithms/__init__.py
pysampling/algorithms/halton.py
pysampling/algorithms/lhs.py
pysampling/algorithms/random.py
pysampling/algorithms/sobol.py
pysampling/resources/sobol_burkardt.dat
pysampling/resources/sobol_joekuo.dat
pysampling/resources/sobol_matlab.dat
pysampling-0.1.2.dist-info/LICENSE
pysampling-0.1.2.dist-info/METADATA
pysampling-0.1.2.dist-info/WHEEL
pysampling-0.1.2.dist-info/top_level.txt
pysampling-0.1.2.dist-info/RECORD
