Metadata-Version: 2.1
Name: pysampling
Version: 0.1.2
Summary: Multi-Objective Optimization in Python
Home-page: https://www.egr.msu.edu/coinlab/blankjul/pysampling/
Author: Julian Blank
Author-email: blankjul@egr.msu.edu
License: Apache License 2.0
Keywords: optimization
Platform: any
Classifier: Intended Audience :: Developers
Classifier: Intended Audience :: Science/Research
Classifier: Operating System :: OS Independent
Classifier: License :: OSI Approved :: Apache Software License
Classifier: Programming Language :: Python
Classifier: Programming Language :: Python :: 3
Classifier: Programming Language :: Python :: 3.6
Classifier: Programming Language :: Python :: 3.7
Classifier: Topic :: Scientific/Engineering
Classifier: Topic :: Scientific/Engineering :: Artificial Intelligence
Classifier: Topic :: Scientific/Engineering :: Mathematics
Requires-Python: >=3.6
Requires-Dist: numpy (>=1.15)
